diex/__init__.py
diex/diex.py
dinoexplorer-1.0.1.dist-info/LICENSE
dinoexplorer-1.0.1.dist-info/METADATA
dinoexplorer-1.0.1.dist-info/WHEEL
dinoexplorer-1.0.1.dist-info/entry_points.txt
dinoexplorer-1.0.1.dist-info/top_level.txt
dinoexplorer-1.0.1.dist-info/RECORD
