Metadata-Version: 2.1
Name: dinoexplorer
Version: 1.0.1
Summary: DINO Explorer: A tool to explore DINO embeddings.
Author: Nityanand Mathur
License: MIT
License-File: LICENSE
Requires-Dist: tqdm
Requires-Dist: pillow
Requires-Dist: rich
Requires-Dist: fiftyone
Requires-Dist: numpy
Requires-Dist: transformers
Requires-Dist: umap-learn
